{
  "members": [
    {
      "Id": 1,
      "avatar_url": "https://pbs.twimg.com/profile_images/1126358830445662208/IPh6PTBx.jpg",
      "name": "Renato Ferreira",
      "birth": 966556800000,
      "gender": "M",
      "created_at": 1588109385915
    }
  ],
  "instructors": [
    {
      "Id": 2,
      "avatar_url": "https://pbs.twimg.com/profile_images/1049383024306081792/cQkGbpRO.jpg",
      "name": "Carla Medeiros",
      "birth": 772502400000,
      "gender": "F",
      "services": "Natação, Spinning",
      "created_at": 1588016706511
    },
    {
      "Id": 3,
      "avatar_url": "https://pbs.twimg.com/profile_images/1022315277139075072/AW-rdWlG.jpg",
      "name": "Diego Farias",
      "birth": null,
      "gender": "M",
      "services": "Crossfit, Musculação, Muai Thai",
      "created_at": 1588016746711
    },
    {
      "Id": 4,
      "avatar_url": "https://pbs.twimg.com/profile_images/1098814780767457281/VUMBKh1U.jpg",
      "name": "Pedro Avelar",
      "birth": null,
      "gender": "M",
      "services": "Yoga, Musculação, Funcional",
      "created_at": 1588016800759
    },
    {
      "Id": 5,
      "avatar_url": "https://pbs.twimg.com/profile_images/681161994641145858/93aChDW6.jpg",
      "name": "Natalia Ramos",
      "birth": 710812800000,
      "gender": "F",
      "services": "Yoga, Funcional",
      "created_at": 1588023124933
    }
  ]
}